<?xml version="1.0" encoding="UTF-8"?>
<data fileName="FasAcTintrM4">
    <header>
    </header>
    <body>
        <field>
            <fieldName>brno</fieldName>
            <fieldType>DISPLAY</fieldType>
            <length>3</length>
            <decimal>0</decimal>
        </field>
        <field>
            <fieldName>filler</fieldName>
            <fieldType>X</fieldType>
            <length>1</length>
            <decimal>0</decimal>
        </field>
        <field>
            <fieldName>amt1</fieldName>
            <fieldType>DISPLAY</fieldType>
            <length>11</length>
            <decimal>0</decimal>
        </field>
        <field>
            <fieldName>filler</fieldName>
            <fieldType>X</fieldType>
            <length>1</length>
            <decimal>0</decimal>
        </field>
        <field>
            <fieldName>amt2</fieldName>
            <fieldType>DISPLAY</fieldType>
            <length>9</length>
            <decimal>0</decimal>
        </field>
        <field>
            <fieldName>filler</fieldName>
            <fieldType>X</fieldType>
            <length>1</length>
            <decimal>0</decimal>
        </field>
        <field>
            <fieldName>rat1</fieldName>
            <fieldType>X</fieldType>
            <length>6</length>
            <decimal>0</decimal>
        </field>
        <field>
            <fieldName>filler</fieldName>
            <fieldType>X</fieldType>
            <length>1</length>
            <decimal>0</decimal>
        </field>
        <field>
            <fieldName>tot1</fieldName>
            <fieldType>DISPLAY</fieldType>
            <length>13</length>
            <decimal>0</decimal>
        </field>
        <field>
            <fieldName>filler</fieldName>
            <fieldType>X</fieldType>
            <length>1</length>
            <decimal>0</decimal>
        </field>
        <field>
            <fieldName>tot2</fieldName>
            <fieldType>DISPLAY</fieldType>
            <length>9</length>
            <decimal>0</decimal>
        </field>
        <field>
            <fieldName>filler</fieldName>
            <fieldType>X</fieldType>
            <length>1</length>
            <decimal>0</decimal>
        </field>
        <field>
            <fieldName>totrat</fieldName>
            <fieldType>X</fieldType>
            <length>6</length>
            <decimal>0</decimal>
        </field>
        <field>
            <fieldName>filler</fieldName>
            <fieldType>X</fieldType>
            <length>1</length>
            <decimal>0</decimal>
        </field>
        <field>
            <fieldName>amt3</fieldName>
            <fieldType>DISPLAY</fieldType>
            <length>12</length>
            <decimal>0</decimal>
        </field>
        <field>
            <fieldName>filler</fieldName>
            <fieldType>X</fieldType>
            <length>1</length>
            <decimal>0</decimal>
        </field>
        <field>
            <fieldName>amt4</fieldName>
            <fieldType>DISPLAY</fieldType>
            <length>9</length>
            <decimal>0</decimal>
        </field>
        <field>
            <fieldName>filler</fieldName>
            <fieldType>X</fieldType>
            <length>1</length>
            <decimal>0</decimal>
        </field>
        <field>
            <fieldName>rat2</fieldName>
            <fieldType>X</fieldType>
            <length>6</length>
            <decimal>0</decimal>
        </field>
        <field>
            <fieldName>filler</fieldName>
            <fieldType>X</fieldType>
            <length>1</length>
            <decimal>0</decimal>
        </field>
        <field>
            <fieldName>amt5</fieldName>
            <fieldType>DISPLAY</fieldType>
            <length>10</length>
            <decimal>0</decimal>
        </field>
        <field>
            <fieldName>filler</fieldName>
            <fieldType>X</fieldType>
            <length>1</length>
            <decimal>0</decimal>
        </field>
        <field>
            <fieldName>amt6</fieldName>
            <fieldType>DISPLAY</fieldType>
            <length>9</length>
            <decimal>0</decimal>
        </field>
        <field>
            <fieldName>filler</fieldName>
            <fieldType>X</fieldType>
            <length>1</length>
            <decimal>0</decimal>
        </field>
        <field>
            <fieldName>rat3</fieldName>
            <fieldType>X</fieldType>
            <length>6</length>
            <decimal>0</decimal>
        </field>
        <field>
            <fieldName>filler</fieldName>
            <fieldType>X</fieldType>
            <length>1</length>
            <decimal>0</decimal>
        </field>
        <field>
            <fieldName>amt7</fieldName>
            <fieldType>DISPLAY</fieldType>
            <length>11</length>
            <decimal>0</decimal>
        </field>
        <field>
            <fieldName>filler</fieldName>
            <fieldType>X</fieldType>
            <length>1</length>
            <decimal>0</decimal>
        </field>
        <field>
            <fieldName>amt8</fieldName>
            <fieldType>DISPLAY</fieldType>
            <length>9</length>
            <decimal>0</decimal>
        </field>
        <field>
            <fieldName>filler</fieldName>
            <fieldType>X</fieldType>
            <length>1</length>
            <decimal>0</decimal>
        </field>
        <field>
            <fieldName>rat4</fieldName>
            <fieldType>X</fieldType>
            <length>6</length>
            <decimal>0</decimal>
        </field>
        <field>
            <fieldName>filler</fieldName>
            <fieldType>X</fieldType>
            <length>1</length>
            <decimal>0</decimal>
        </field>
        <field>
            <fieldName>amt9</fieldName>
            <fieldType>DISPLAY</fieldType>
            <length>10</length>
            <decimal>0</decimal>
        </field>
        <field>
            <fieldName>filler</fieldName>
            <fieldType>X</fieldType>
            <length>1</length>
            <decimal>0</decimal>
        </field>
        <field>
            <fieldName>amt10</fieldName>
            <fieldType>DISPLAY</fieldType>
            <length>9</length>
            <decimal>0</decimal>
        </field>
        <field>
            <fieldName>filler</fieldName>
            <fieldType>X</fieldType>
            <length>1</length>
            <decimal>0</decimal>
        </field>
        <field>
            <fieldName>rat5</fieldName>
            <fieldType>X</fieldType>
            <length>6</length>
            <decimal>0</decimal>
        </field>
        <field>
            <fieldName>cr</fieldName>
            <fieldType>X</fieldType>
            <length>1</length>
            <decimal>0</decimal>
        </field>
        <field>
            <fieldName>lf</fieldName>
            <fieldType>X</fieldType>
            <length>1</length>
            <decimal>0</decimal>
        </field>
    </body>
    <footer>
    </footer>
</data>

